main.py
example_123-0.1.0.dist-info/METADATA
example_123-0.1.0.dist-info/WHEEL
example_123-0.1.0.dist-info/RECORD
